Workbook

Sheet RELATIVE REFERENCE
A1: Month | B1: Total Revenue | C1: Total Expenses | D1: Net Income
A2: Jan | B2: 730 | C2: 413 | D2: =B2-C2 -> 317
A3: Feb | B3: 102 | C3: 169 | D3: =B3-C3 -> -67
A4: Mar | B4: 158 | C4: 258 | D4: =B4-C4 -> -100
A5: Apr | B5: 505 | C5: 429 | D5: =B5-C5 -> 76
A6: May | B6: 925 | C6: 270 | D6: =B6-C6 -> 655
A7: Jun | B7: 242 | C7: 129 | D7: =B7-C7 -> 113
A8: Jul | B8: 636 | C8: 79 | D8: =B8-C8 -> 557
A9: Aug | B9: 213 | C9: 123 | D9: =B9-C9 -> 90

Sheet RELATIVE REFERENCE1
A1: Unit Sales | B1: Quantity | C1: Line Sales
A2: 10 | B2: 2 | C2: =A2*B2+D2 -> 24 | D2: 4
A3: 20 | B3: 9 | C3: =A3*B3+4 -> 184 | D3: 5
A4: 30 | B4: 4 | C4: =A4*B4+4 -> 124 | D4: 6
A5: 40 | B5: 10 | C5: =A5*B5+4 -> 404 | D5: 7
A6: 50 | B6: 1 | C6: =A6*B6+4 -> 54 | D6: 8
A7: 60 | B7: 6 | C7: =A7*B7+4 -> 364 | D7: 9
A8: 70 | B8: 4 | C8: =A8*B8+4 -> 284 | D8: 10
A9: 80 | B9: 2 | C9: =A9*B9+4 -> 164 | D9: 11

Sheet Sheet4
J7: 100

Sheet Absoulute Reference
A1: Name | B1: Score | C1: Maximum Marks | D1: Percentage
A2: Peter | B2: 42 | C2: 100 | D2: =B2/C2 -> 0.42 | E2: =B2/100 -> 0.42 | F2: =B2/$C$2 -> 0.42
A3: Vihaan | B3: 76 | D3: =B3/C3 -> #DIV/0! | E3: =B3/100 -> 0.76 | F3: =B3/$C$2 -> 0.76
A4: Atul | B4: 100 | D4: =B4/C4 -> #DIV/0! | E4: =B4/100 -> 1 | F4: =B4/$C$2 -> 1
A5: Pavan | B5: 65 | D5: =B5/C5 -> #DIV/0! | E5: =B5/100 -> 0.65 | F5: =B5/$C$2 -> 0.65
A6: Ramakant | B6: 94 | D6: =B6/C6 -> #DIV/0! | E6: =B6/100 -> 0.94 | F6: =B6/$C$2 -> 0.94
A7: Ajinkya | B7: 87 | D7: =B7/C7 -> #DIV/0! | E7: =B7/100 -> 0.87 | F7: =B7/$C$2 -> 0.87 | J7: 35 | N7: =J7/$C$2 -> 0.35
A8: Altaf | B8: 58 | D8: =B8/C8 -> #DIV/0! | E8: =B8/100 -> 0.58 | F8: =B8/$C$2 -> 0.58
A9: Pandhari | B9: 66 | D9: =B9/C9 -> #DIV/0! | E9: =B9/100 -> 0.66 | F9: =B9/$C$2 -> 0.66
A10: Dollie | B10: 63 | D10: =B10/C10 -> #DIV/0! | E10: =B10/100 -> 0.63 | F10: =B10/$C$2 -> 0.63
A11: Rahul | B11: 100 | D11: =B11/C11 -> #DIV/0! | E11: =B11/100 -> 1 | F11: =B11/$C$2 -> 1
A17: Name | B17: Score | C17: Maximum Marks | D17: Percentage
A18: Peter | B18: 42 | D18: =B18/C22 -> 0.42 | E18: =B18/100 -> 0.42 | F18: =B18/$C$22 -> 0.42
A19: Vihaan | B19: 76 | D19: =B19/C23 -> #DIV/0! | E19: =B19/100 -> 0.76 | F19: =B19/$C$22 -> 0.76
A20: Atul | B20: 100 | D20: =B20/C24 -> #DIV/0! | E20: =B20/100 -> 1 | F20: =B20/$C$22 -> 1
A21: Pavan | B21: 65 | D21: =B21/C25 -> #DIV/0! | E21: =B21/100 -> 0.65 | F21: =B21/$C$22 -> 0.65
A22: Ramakant | B22: 94 | C22: 100 | D22: =B22/C26 -> #DIV/0! | E22: =B22/100 -> 0.94 | F22: =B22/$C$22 -> 0.94
A23: Ajinkya | B23: 87 | D23: =B23/C27 -> #DIV/0! | E23: =B23/100 -> 0.87 | F23: =B23/$C$22 -> 0.87
A24: Altaf | B24: 58 | D24: =B24/C28 -> #DIV/0! | E24: =B24/100 -> 0.58 | F24: =B24/$C$22 -> 0.58
A25: Pandhari | B25: 66 | D25: =B25/C29 -> #DIV/0! | E25: =B25/100 -> 0.66 | F25: =B25/$C$22 -> 0.66
A26: Dollie | B26: 63 | D26: =B26/C30 -> #DIV/0! | E26: =B26/100 -> 0.63 | F26: =B26/$C$22 -> 0.63
A27: Rahul | B27: 100 | D27: =B27/C31 -> #DIV/0! | E27: =B27/100 -> 1 | F27: =B27/$C$22 -> 1
A33: Name | B33: Score | C33: Percentage
A34: Peter | B34: 42 | C34: =B34/Sheet4!J7 -> 0.42 | D34: =B34/100 -> 0.42 | E34: =B34/Sheet4!$J$7 -> 0.42
A35: Vihaan | B35: 76 | C35: =B35/Sheet4!J8 -> #DIV/0! | D35: =B35/100 -> 0.76 | E35: =B35/Sheet4!$J$7 -> 0.76
A36: Atul | B36: 100 | C36: =B36/Sheet4!J9 -> #DIV/0! | D36: =B36/100 -> 1 | E36: =B36/Sheet4!$J$7 -> 1
A37: Pavan | B37: 65 | C37: =B37/Sheet4!J10 -> #DIV/0! | D37: =B37/100 -> 0.65 | E37: =B37/Sheet4!$J$7 -> 0.65
A38: Ramakant | B38: 94 | C38: =B38/Sheet4!J11 -> #DIV/0! | D38: =B38/100 -> 0.94 | E38: =B38/Sheet4!$J$7 -> 0.94
A39: Ajinkya | B39: 87 | C39: =B39/Sheet4!J12 -> #DIV/0! | D39: =B39/100 -> 0.87 | E39: =B39/Sheet4!$J$7 -> 0.87
A40: Altaf | B40: 58 | C40: =B40/Sheet4!J13 -> #DIV/0! | D40: =B40/100 -> 0.58 | E40: =B40/Sheet4!$J$7 -> 0.58
A41: Pandhari | B41: 66 | C41: =B41/Sheet4!J14 -> #DIV/0! | D41: =B41/100 -> 0.66 | E41: =B41/Sheet4!$J$7 -> 0.66
A42: Dollie | B42: 63 | C42: =B42/Sheet4!J15 -> #DIV/0! | D42: =B42/100 -> 0.63 | E42: =B42/Sheet4!$J$7 -> 0.63
A43: Rahul | B43: 100 | C43: =B43/Sheet4!J16 -> #DIV/0! | D43: =B43/100 -> 1 | E43: =B43/Sheet4!$J$7 -> 1

Sheet Absoulute Reference1
B2: Tax Rate | C2: 0.18
B5: Unit Sales | C5: Quantity | D5: Line Sales | E5: Tax Amount
B6: 50 | C6: 2 | D6: =B6*C6 -> 100 | E6: =D6*$C$2 -> 18
B7: 20 | C7: 9 | D7: =B7*C7 -> 180 | E7: =D7*$C$2 -> 32.4
B8: 30 | C8: 4 | D8: =B8*C8 -> 120 | E8: =D8*$C$2 -> 21.6
B9: 40 | C9: 10 | D9: =B9*C9 -> 400 | E9: =D9*$C$2 -> 72
B10: 50 | C10: 1 | D10: =B10*C10 -> 50 | E10: =D10*$C$2 -> 9
B11: 60 | C11: 6 | D11: =B11*C11 -> 360 | E11: =D11*$C$2 -> 64.8
B12: 70 | C12: 4 | D12: =B12*C12 -> 280 | E12: =D12*$C$2 -> 50.4
B13: 80 | C13: 2 | D13: =B13*C13 -> 160 | E13: =D13*$C$2 -> 28.8

Sheet MixedCellReference
G4: Term
G5: 1 | H5: 2 | I5: 3 | J5: 4 | K5: 5
E6: Amount | F6: 10 | G6: =$F6*G$5 -> 10 | H6: =$F6*H$5 -> 20 | I6: =$F6*I$5 -> 30 | J6: =$F6*J$5 -> 40 | K6: =$F6*K$5 -> 50
F7: 20 | G7: =$F7*G$5 -> 20 | H7: =$F7*H$5 -> 40 | I7: =$F7*I$5 -> 60 | J7: =$F7*J$5 -> 80 | K7: =$F7*K$5 -> 100
F8: 30 | G8: =$F8*G$5 -> 30 | H8: =$F8*H$5 -> 60 | I8: =$F8*I$5 -> 90 | J8: =$F8*J$5 -> 120 | K8: =$F8*K$5 -> 150
F9: 40 | G9: =$F9*G$5 -> 40 | H9: =$F9*H$5 -> 80 | I9: =$F9*I$5 -> 120 | J9: =$F9*J$5 -> 160 | K9: =$F9*K$5 -> 200
F10: 50 | G10: =$F10*G$5 -> 50 | H10: =$F10*H$5 -> 100 | I10: =$F10*I$5 -> 150 | J10: =$F10*J$5 -> 200 | K10: =$F10*K$5 -> 250
